dbs/apis/__init__.py
dbs/apis/dbsClient.py
dbs/exceptions/__init__.py
dbs/exceptions/dbsClientException.py
dbs3_client-4.0.12.dist-info/LICENSE
dbs3_client-4.0.12.dist-info/METADATA
dbs3_client-4.0.12.dist-info/WHEEL
dbs3_client-4.0.12.dist-info/top_level.txt
dbs3_client-4.0.12.dist-info/RECORD
